pysqa/__init__.py
pysqa/__main__.py
pysqa/_version.py
pysqa/queueadapter.py
pysqa/base/__init__.py
pysqa/base/abstract.py
pysqa/base/cmd.py
pysqa/base/config.py
pysqa/base/core.py
pysqa/base/modular.py
pysqa/base/remote.py
pysqa/base/validate.py
pysqa/wrapper/__init__.py
pysqa/wrapper/abstract.py
pysqa/wrapper/flux.py
pysqa/wrapper/gent.py
pysqa/wrapper/lsf.py
pysqa/wrapper/moab.py
pysqa/wrapper/sge.py
pysqa/wrapper/slurm.py
pysqa/wrapper/torque.py
pysqa-0.3.4.dist-info/METADATA
pysqa-0.3.4.dist-info/WHEEL
pysqa-0.3.4.dist-info/entry_points.txt
pysqa-0.3.4.dist-info/licenses/LICENSE
pysqa-0.3.4.dist-info/RECORD
