Metadata-Version: 2.4
Name: pysqa
Version: 0.3.4
Summary: Simple HPC queuing system adapter for Python on based jinja templates to automate the submission script creation.
Project-URL: Homepage, https://github.com/pyiron/pysqa
Project-URL: Documentation, https://pysqa.readthedocs.io
Project-URL: Repository, https://github.com/pyiron/pysqa
Author-email: Jan Janssen <janssen@mpie.de>
License: BSD 3-Clause License
License-File: LICENSE
Keywords: pyiron
Classifier: Development Status :: 5 - Production/Stable
Classifier: Intended Audience :: Science/Research
Classifier: License :: OSI Approved :: BSD License
Classifier: Operating System :: OS Independent
Classifier: Programming Language :: Python :: 3.9
Classifier: Programming Language :: Python :: 3.10
Classifier: Programming Language :: Python :: 3.11
Classifier: Programming Language :: Python :: 3.12
Classifier: Programming Language :: Python :: 3.13
Classifier: Programming Language :: Python :: 3.14
Classifier: Topic :: Scientific/Engineering :: Physics
Requires-Python: <3.15,>=3.9
Requires-Dist: jinja2<=3.1.6,>=2.11.3
Requires-Dist: pandas<=3.0.0,>=1.5.3
Requires-Dist: pyyaml<=6.0.3,>=5.3.1
Provides-Extra: remote
Requires-Dist: paramiko<=4.0.0,>=2.7.1; extra == 'remote'
Requires-Dist: tqdm<=4.67.1,>=4.66.1; extra == 'remote'
Provides-Extra: sge
Requires-Dist: defusedxml<=0.7.1,>=0.7.0; extra == 'sge'
Provides-Extra: twofactor
Requires-Dist: pyauthenticator==0.3.0; extra == 'twofactor'
